{
  "swagger": "2.0",
  "info": {
    "title": "hashicorp/cloud/common/sorting.proto",
    "version": "version not set"
  },
  "consumes": [
    "application/json"
  ],
  "produces": [
    "application/json"
  ],
  "paths": {},
  "definitions": {
    "google.protobuf.Any": {
      "type": "object",
      "properties": {
        "type_url": {
          "type": "string"
        },
        "value": {
          "type": "string",
          "format": "byte"
        }
      }
    },
    "grpc.gateway.runtime.Error": {
      "type": "object",
      "properties": {
        "error": {
          "type": "string"
        },
        "code": {
          "type": "integer",
          "format": "int32"
        },
        "message": {
          "type": "string"
        },
        "details": {
          "type": "array",
          "items": {
            "$ref": "#/definitions/google.protobuf.Any"
          }
        }
      }
    },
    "hashicorp.cloud.common.SortingRequest": {
      "type": "object",
      "properties": {
        "order_by": {
          "type": "array",
          "items": {
            "type": "string"
          },
          "description": "Specifies the list of per field ordering that should be used for sorting. \nThe order matters as rows are sorted in order by fields and when the field\nmatches, the next field is used to tie break the ordering.\nThe per field default ordering is ascending.  \n\nThe fields should be immutabile, unique, and orderable. If the field is\nnot unique, more than one sort fields should be passed.\n\nExample: oder_by=name,age desc,created_at asc\nIn that case, 'name' will get the default 'ascending' order."
        }
      },
      "description": "SortingRequest are the parameters for a sorted list request."
    }
  }
}
